taxi_etl/__init__.py
taxi_etl-11.11.3.dist-info/LICENSE
taxi_etl-11.11.3.dist-info/METADATA
taxi_etl-11.11.3.dist-info/WHEEL
taxi_etl-11.11.3.dist-info/top_level.txt
taxi_etl-11.11.3.dist-info/RECORD
